MANIFEST.in
MIT-LICENSE.txt
README.rst
requirements.txt
setup.py
audiofield/__init__.py
audiofield/__init__.pyc
audiofield/admin.py
audiofield/admin.pyc
audiofield/fields.py
audiofield/fields.pyc
audiofield/forms.py
audiofield/forms.pyc
audiofield/intermediate_model_base_class.pyc
audiofield/models.py
audiofield/models.pyc
audiofield/tasks.py
audiofield/tasks.pyc
audiofield/tests.py
audiofield/widgets.py
audiofield/widgets.pyc
audiofield/locale/en/LC_MESSAGES/django.mo
audiofield/locale/en/LC_MESSAGES/django.po
audiofield/locale/es/LC_MESSAGES/django.mo
audiofield/locale/es/LC_MESSAGES/django.po
audiofield/locale/pt/LC_MESSAGES/django.mo
audiofield/locale/pt/LC_MESSAGES/django.po
audiofield/locale/zh/LC_MESSAGES/django.mo
audiofield/locale/zh/LC_MESSAGES/django.po
audiofield/middleware/__init__.py
audiofield/middleware/__init__.pyc
audiofield/middleware/threadlocals.py
audiofield/middleware/threadlocals.pyc
audiofield/migrations/0001_initial.py
audiofield/migrations/0001_initial.pyc
audiofield/migrations/0002_auto_20180121_0750.py
audiofield/migrations/0002_auto_20180121_0750.pyc
audiofield/migrations/0003_auto_20220520_1655.py
audiofield/migrations/0003_auto_20220520_1655.pyc
audiofield/migrations/__init__.py
audiofield/migrations/__init__.pyc
audiofield/static/audiofield/flashblock/basic.html
audiofield/static/audiofield/flashblock/flashblock.css
audiofield/static/audiofield/flashblock/index.html
audiofield/static/audiofield/flashblock/method1/flashblock.css
audiofield/static/audiofield/flashblock/method1/flashblock.js
audiofield/static/audiofield/flashblock/method1/index.html
audiofield/static/audiofield/page-player/basic.html
audiofield/static/audiofield/page-player/css/demo.css
audiofield/static/audiofield/page-player/css/optional-annotations.css
audiofield/static/audiofield/page-player/css/optional-themes.css
audiofield/static/audiofield/page-player/css/page-player.css
audiofield/static/audiofield/page-player/image/divot-bottom.png
django_audiofield.egg-info/PKG-INFO
django_audiofield.egg-info/SOURCES.txt
django_audiofield.egg-info/dependency_links.txt
django_audiofield.egg-info/not-zip-safe
django_audiofield.egg-info/requires.txt
django_audiofield.egg-info/top_level.txt