Metadata-Version: 1.1
Name: django-audiofield
Version: 0.10.1
Summary: Django application to upload and convert audio files (mp3, wav and ogg format)
Home-page: http://github.com/Star2Billing/django-audiofield
Author: Belaid Arezqui
Author-email: areski@gmail.com
License: MIT License
Platform: UNKNOWN
Classifier: Development Status :: 5 - Production/Stable
Classifier: Environment :: Web Environment
Classifier: Framework :: Django
Classifier: Intended Audience :: Developers
Classifier: License :: OSI Approved :: MIT License
Classifier: Operating System :: OS Independent
Classifier: Programming Language :: Python
Classifier: Topic :: Software Development :: Libraries :: Python Modules
